hpc_helper/__init__.py
hpc_helper/_hpc_helper.py
hpc_helper/_types.py
hpc_helper-0.3.2.dist-info/LICENSE
hpc_helper-0.3.2.dist-info/METADATA
hpc_helper-0.3.2.dist-info/WHEEL
hpc_helper-0.3.2.dist-info/RECORD
