Metadata-Version: 2.1
Name: hpc_helper
Version: 0.3.2
Summary: Python package with helper functions for working with FAU's High Performance Cluster (HPC).
Home-page: https://github.com/mad-lab-fau/hpc-helper
License: MIT
Author: Robert Richer
Author-email: robert.richer@fau.de
Requires-Python: >=3.8,<3.11
Classifier: License :: OSI Approved :: MIT License
Classifier: Programming Language :: Python :: 3
Classifier: Programming Language :: Python :: 3.8
Classifier: Programming Language :: Python :: 3.9
Classifier: Programming Language :: Python :: 3.10
Project-URL: Repository, https://github.com/mad-lab-fau/hpc-helper
